skeletoken/__init__.py
skeletoken/addedtoken.py
skeletoken/base.py
skeletoken/common.py
skeletoken/decoders.py
skeletoken/merges.py
skeletoken/model_delta.py
skeletoken/models.py
skeletoken/normalizers.py
skeletoken/padding.py
skeletoken/postprocessors.py
skeletoken/pretokenizers.py
skeletoken/py.typed
skeletoken/truncation.py
skeletoken/version.py
skeletoken/vocabulary.py
skeletoken/decase/__init__.py
skeletoken/decase/byte_handlers.py
skeletoken/decase/decase.py
skeletoken-0.2.1.dist-info/licenses/LICENSE
skeletoken-0.2.1.dist-info/METADATA
skeletoken-0.2.1.dist-info/WHEEL
skeletoken-0.2.1.dist-info/top_level.txt
skeletoken-0.2.1.dist-info/RECORD
