Metadata-Version: 2.4
Name: skeletoken
Version: 0.2.1
Summary: Datamodels for HF tokenizers
Requires-Python: >=3.10
License-File: LICENSE
Requires-Dist: tokenizers
Requires-Dist: pydantic
Requires-Dist: transformers
Requires-Dist: protobuf
Provides-Extra: dev
Requires-Dist: ipython; extra == "dev"
Requires-Dist: mypy; extra == "dev"
Requires-Dist: pre-commit; extra == "dev"
Requires-Dist: pytest; extra == "dev"
Requires-Dist: pytest-coverage; extra == "dev"
Requires-Dist: ruff; extra == "dev"
Dynamic: license-file
